{"Command":"StateEstimate","Content":{"FState":[{"FStateID":10684,"SampleType":1,"FDevNum":4,"Probability":1.73017E-6,"Durition":3.46034,"StateNum":1,"FLossGen":844.7,"FLossGenCap":928.4,"FLossLoad":0.0,"MIsland":0,"MIslandInsGen":0.0,"MIslandCutGen":0.0,"MIslandOutLoad":0.0,"BalanceInsGen":424.9,"BalanceCutGen":0.0,"BalanceCutLoad":419.8,"OverLimit":1,"ELimit":0,"ELimitCutGen":36.5653,"ELimitInsGen":36.5653,"ELimitCutLoad":0.0,"ELimitResult":1,"MaxFaultZone":0,"MaxFaultRatio":0.278937,"FaultGrade":2,"MSoutIndex":-1,"Estimated":1}],"FStateOvlDev":[{"FStateId":10684,"FStateNo":0,"DevTyp":4,"DevIdx":30,"OvLmtP":192.262,"Rated":174.96,"AdLmtP":155.697}],"FStateOvlAd":[{"FStateId":10684,"FStateNo":0,"OvlDevTyp":4,"OvlDevice":30,"AdjDevTyp":6,"AdjDevice":22,"AdjValue":-36.5653},{"FStateId":10684,"FStateNo":0,"OvlDevTyp":4,"OvlDevice":30,"AdjDevTyp":6,"AdjDevice":10,"AdjValue":36.5653}],"FStateMIsland":[],"Value":"1"}}