{"Command":"StateEstimate","Content":{"FState":[{"FStateID":10925,"SampleType":1,"FDevNum":4,"Probability":1.02587E-6,"Durition":2.05173,"StateNum":1,"FLossGen":507.25,"FLossGenCap":598.95,"FLossLoad":0.0,"MIsland":0,"MIslandInsGen":0.0,"MIslandCutGen":0.0,"MIslandOutLoad":0.0,"BalanceInsGen":416.9,"BalanceCutGen":0.0,"BalanceCutLoad":90.35,"OverLimit":1,"ELimit":0,"ELimitCutGen":20.6549,"ELimitInsGen":20.6549,"ELimitCutLoad":0.0,"ELimitResult":1,"MaxFaultZone":0,"MaxFaultRatio":0.0600332,"FaultGrade":0,"MSoutIndex":-1,"Estimated":1}],"FStateOvlDev":[{"FStateId":10925,"FStateNo":0,"DevTyp":4,"DevIdx":30,"OvLmtP":177.813,"Rated":174.96,"AdLmtP":157.158}],"FStateOvlAd":[{"FStateId":10925,"FStateNo":0,"OvlDevTyp":4,"OvlDevice":30,"AdjDevTyp":6,"AdjDevice":22,"AdjValue":-20.6549},{"FStateId":10925,"FStateNo":0,"OvlDevTyp":4,"OvlDevice":30,"AdjDevTyp":6,"AdjDevice":8,"AdjValue":20.6549}],"FStateMIsland":[],"Value":"1"}}