{"Command":"StateEstimate","Content":{"FState":[{"memIndex":13677,"FStateID":13678,"SampleType":1,"FDevNum":5,"Probability":8.437E-6,"Durition":16.874,"StateNum":1,"FLossGen":0.0,"FLossGenCap":0.0,"FLossLoad":0.0,"MIsland":0,"MIslandInsGen":0.0,"MIslandCutGen":0.0,"MIslandOutLoad":0.0,"BalanceInsGen":0.0,"BalanceCutGen":0.0,"BalanceCutLoad":0.0,"OverLimit":0,"ELimit":0,"ELimitCutGen":0.0,"ELimitInsGen":0.0,"ELimitCutLoad":0.0,"ELimitResult":0,"MaxFaultZone":0,"MaxFaultRatio":0.0,"FaultGrade":0,"MSoutIndex":-1,"Estimated":1}],"FStateFDev":[{"memIndex":48603,"FStateId":13678,"FStateNo":13677,"FDevTyp":6,"FDevIdx":16,"DFltPos":0,"DFltTyp":1},{"memIndex":48604,"FStateId":13678,"FStateNo":13677,"FDevTyp":4,"FDevIdx":3,"DFltPos":0,"DFltTyp":4},{"memIndex":48605,"FStateId":13678,"FStateNo":13677,"FDevTyp":6,"FDevIdx":15,"DFltPos":0,"DFltTyp":1},{"memIndex":48606,"FStateId":13678,"FStateNo":13677,"FDevTyp":6,"FDevIdx":5,"DFltPos":0,"DFltTyp":1},{"memIndex":48607,"FStateId":13678,"FStateNo":13677,"FDevTyp":6,"FDevIdx":14,"DFltPos":0,"DFltTyp":1}],"Value":"13678"}}